{
  "id": "MC1255714",
  "versions": [
    {
      "capturedAt": "2026-03-19T04:42:23.787Z",
      "source": "git",
      "sha": "426a89083fd255d755bbfe90a3df3717b06377eb",
      "message": {
        "ActionRequiredByDateTime": null,
        "Attachments": null,
        "AttachmentsArchive": null,
        "Body": {
          "Content": "On March 18, 2026, we published the <a href=\"https://aka.ms/14128-release-plans\" target=\"_blank\">2026 release wave 1 plans</a> for <a href=\"https://aka.ms/Dynamics365ReleasePlan\" target=\"_blank\">Dynamics 365</a>, <a href=\"https://aka.ms/PowerPlatformReleasePlanner\" target=\"_blank\">Microsoft Power Platform</a>, and <a href=\"https://aka.ms/CopilotReleasePlanner\" target=\"_blank\">Role-based Copilot offerings</a> which is a compilation of new capabilities that will be released between April 2026 through September 2026. The new features and enhancements provide you with significant capabilities to help transform your business using our applications.<br><br><b>What actions do I need to take?</b><br>You can use the <a href=\"https://aka.ms/Dynamics365ReleasePlan\" target=\"_blank\">Release planner</a> to view and manage release plans across all active release waves in a unified and interactive interface, while giving them the option to personalize, filter, sort, and collaborate.<br><br>We've done this work to help you—our partners, customers, and users—drive the digital transformation of your business on your terms. Get ready to share your feedback in the community forum for <a href=\"https://community.dynamics.com/\" target=\"_blank\">Dynamics 365</a> or <a href=\"https://powerusers.microsoft.com/\" target=\"_blank\">Power Platform</a>.",
          "ContentType": "html"
        },
        "Category": "stayInformed",
        "Details": [],
        "EndDateTime": "2026-04-19T04:39:14Z",
        "HasAttachments": false,
        "Id": "MC1255714",
        "IsMajorChange": false,
        "LastModifiedDateTime": "2026-03-19T04:42:23.787Z",
        "Services": [
          "Dynamics 365 Apps"
        ],
        "Severity": "normal",
        "StartDateTime": "2026-03-19T04:39:14Z",
        "Tags": [],
        "Title": "Dynamics 365, Power Platform, and Role-based Copilot offerings 2026 release wave 1 plans available now",
        "ViewPoint": {
          "IsArchived": null,
          "IsFavorited": null,
          "IsRead": null
        },
        "AdditionalProperties": {}
      }
    }
  ]
}