{
  "id": "RM409534",
  "versions": [
    {
      "capturedAt": "2026-03-12T23:00:54.0000000Z",
      "source": "git",
      "sha": "bc5eb4243809619b52baa0c9c57e4ec6dc6fcded",
      "message": {
        "ActionRequiredByDateTime": null,
        "Attachments": null,
        "AttachmentsArchive": null,
        "Body": {
          "Content": "<p>Microsoft Teams Rooms on Windows will provide native Pan-Tilt-Zoom (PTZ) controls for connected cameras that support this capability. The feature will initially contain limited support for cameras with mechanical/optical PTZ, with digital PTZ to come in the future.</p>\n<p><b>GA date:</b> September CY2026</p>",
          "ContentType": "html",
          "Markdown": "Microsoft Teams Rooms on Windows will provide native Pan-Tilt-Zoom (PTZ) controls for connected cameras that support this capability. The feature will initially contain limited support for cameras with mechanical/optical PTZ, with digital PTZ to come in the future.\n\nGA date: September CY2026"
        },
        "Category": "roadmap",
        "Details": [
          {
            "Name": "RoadmapIds",
            "Value": "409534"
          },
          {
            "Name": "SourceId",
            "Value": "409534"
          },
          {
            "Name": "RoadmapLink",
            "Value": "https://www.microsoft.com/microsoft-365/roadmap?id=409534"
          },
          {
            "Name": "Summary",
            "Value": "Microsoft Teams Rooms on Windows will provide native Pan-Tilt-Zoom (PTZ) controls for connected cameras that support this capability. The feature will initially contain limited support for cameras with mechanical/optical PTZ, with digital PTZ to come in the future."
          },
          {
            "Name": "Status",
            "Value": "In development"
          },
          {
            "Name": "ReleasePhase",
            "Value": "General Availability"
          },
          {
            "Name": "CloudInstances",
            "Value": "DoD, GCC, GCC High, Worldwide (Standard Multi-Tenant)"
          },
          {
            "Name": "Platforms",
            "Value": "Desktop"
          }
        ],
        "EndDateTime": null,
        "HasAttachments": false,
        "Id": "RM409534",
        "IsMajorChange": false,
        "LastModifiedDateTime": "2026-03-12T23:00:54.0000000Z",
        "Services": [
          "Microsoft Teams"
        ],
        "Severity": "normal",
        "Source": "roadmap",
        "StartDateTime": "2024-07-26T22:30:19.0000000Z",
        "Tags": [
          "In development",
          "General Availability",
          "Worldwide (Standard Multi-Tenant)",
          "GCC",
          "GCC High",
          "DoD"
        ],
        "Title": "Microsoft Teams: Local PTZ for Microsoft Teams Rooms on Windows",
        "ViewPoint": {
          "IsArchived": null,
          "IsFavorited": null,
          "IsRead": null
        },
        "AdditionalProperties": {}
      }
    }
  ]
}