{
  "id": "RM537276",
  "versions": [
    {
      "capturedAt": "2026-03-16T23:00:10.0000000Z",
      "source": "git",
      "sha": "bc5eb4243809619b52baa0c9c57e4ec6dc6fcded",
      "message": {
        "ActionRequiredByDateTime": null,
        "Attachments": null,
        "AttachmentsArchive": null,
        "Body": {
          "Content": "<p>User-Based Aggregation consolidates DLP alerts by user identity i.e. a DLP rule violations, in a specified aggregation time window, of the same rule and single user will be aggregated into a single alert enabling quicker triage and remediation. Instead of reviewing alerts containing rule match events of multiple users, DLP admin can now analyze grouped DLP rule match events per user, gaining insights into repeated policy violations and anomalous behavior.</p>\n<p><b>GA date:</b> February CY2026</p>",
          "ContentType": "html",
          "Markdown": "User-Based Aggregation consolidates DLP alerts by user identity i.e. a DLP rule violations, in a specified aggregation time window, of the same rule and single user will be aggregated into a single alert enabling quicker triage and remediation. Instead of reviewing alerts containing rule match events of multiple users, DLP admin can now analyze grouped DLP rule match events per user, gaining insights into repeated policy violations and anomalous behavior.\n\nGA date: February CY2026"
        },
        "Category": "roadmap",
        "Details": [
          {
            "Name": "RoadmapIds",
            "Value": "537276"
          },
          {
            "Name": "SourceId",
            "Value": "537276"
          },
          {
            "Name": "RoadmapLink",
            "Value": "https://www.microsoft.com/microsoft-365/roadmap?id=537276"
          },
          {
            "Name": "Summary",
            "Value": "User-Based Aggregation consolidates DLP alerts by user identity i.e. a DLP rule violations, in a specified aggregation time window, of the same rule and single user will be aggregated into a single alert enabling quicker triage and remediation. Instead of reviewing alerts containing rule match events of multiple users, DLP admin can now analyze grouped DLP rule match events per user, gaining insights into repeated policy violations and anomalous behavior."
          },
          {
            "Name": "Status",
            "Value": "Launched"
          },
          {
            "Name": "ReleasePhase",
            "Value": "General Availability"
          },
          {
            "Name": "CloudInstances",
            "Value": "DoD, GCC, GCC High"
          },
          {
            "Name": "Platforms",
            "Value": "Web"
          }
        ],
        "EndDateTime": null,
        "HasAttachments": false,
        "Id": "RM537276",
        "IsMajorChange": false,
        "LastModifiedDateTime": "2026-03-16T23:00:10.0000000Z",
        "Services": [
          "Microsoft Purview"
        ],
        "Severity": "normal",
        "Source": "roadmap",
        "StartDateTime": "2025-12-10T00:15:49.0000000Z",
        "Tags": [
          "Launched",
          "General Availability",
          "GCC",
          "GCC High",
          "DoD"
        ],
        "Title": "Microsoft Purview: Data Loss Prevention-User based alert aggregation",
        "ViewPoint": {
          "IsArchived": null,
          "IsFavorited": null,
          "IsRead": null
        },
        "AdditionalProperties": {}
      }
    }
  ]
}