{
  "id": "RM543421",
  "versions": [
    {
      "capturedAt": "2026-03-11T23:30:17.0000000Z",
      "source": "git",
      "sha": "bc5eb4243809619b52baa0c9c57e4ec6dc6fcded",
      "message": {
        "ActionRequiredByDateTime": null,
        "Attachments": null,
        "AttachmentsArchive": null,
        "Body": {
          "Content": "<p>PowerPoint Agent helps you build polished presentations with strong storytelling and visual structure. It streamlines research, formatting, and layout so you can stay focused on your message. Use multi‑turn chat to refine content or open the deck in PowerPoint for full editing and collaboration. Ideal for executive presentations, strategic updates, and market overviews. Available to Microsoft 365 users with or without a Microsoft 365 Copilot license.</p>\n<p><b>GA date:</b> March CY2026</p>\n<p><b>Preview date:</b> November CY2025</p>",
          "ContentType": "html",
          "Markdown": "PowerPoint Agent helps you build polished presentations with strong storytelling and visual structure. It streamlines research, formatting, and layout so you can stay focused on your message. Use multi‑turn chat to refine content or open the deck in PowerPoint for full editing and collaboration. Ideal for executive presentations, strategic updates, and market overviews. Available to Microsoft 365 users with or without a Microsoft 365 Copilot license.\n\nGA date: March CY2026\n\nPreview date: November CY2025"
        },
        "Category": "roadmap",
        "Details": [
          {
            "Name": "RoadmapIds",
            "Value": "543421"
          },
          {
            "Name": "SourceId",
            "Value": "543421"
          },
          {
            "Name": "RoadmapLink",
            "Value": "https://www.microsoft.com/microsoft-365/roadmap?id=543421"
          },
          {
            "Name": "Summary",
            "Value": "PowerPoint Agent helps you build polished presentations with strong storytelling and visual structure. It streamlines research, formatting, and layout so you can stay focused on your message. Use multi‑turn chat to refine content or open the deck in PowerPoint for full editing and collaboration. Ideal for executive presentations, strategic updates, and market overviews. Available to Microsoft 365 users with or without a Microsoft 365 Copilot license."
          },
          {
            "Name": "Status",
            "Value": "Rolling out"
          },
          {
            "Name": "ReleasePhase",
            "Value": "General Availability, Preview"
          },
          {
            "Name": "CloudInstances",
            "Value": "Worldwide (Standard Multi-Tenant)"
          },
          {
            "Name": "Platforms",
            "Value": "Desktop, Mac, Web"
          }
        ],
        "EndDateTime": null,
        "HasAttachments": false,
        "Id": "RM543421",
        "IsMajorChange": false,
        "LastModifiedDateTime": "2026-03-11T23:30:17.0000000Z",
        "Services": [
          "PowerPoint",
          "Microsoft Copilot (Microsoft 365)"
        ],
        "Severity": "normal",
        "Source": "roadmap",
        "StartDateTime": "2025-12-19T23:00:49.0000000Z",
        "Tags": [
          "Rolling out",
          "General Availability",
          "Preview",
          "Worldwide (Standard Multi-Tenant)"
        ],
        "Title": "Microsoft Copilot (Microsoft 365): PowerPoint Agent",
        "ViewPoint": {
          "IsArchived": null,
          "IsFavorited": null,
          "IsRead": null
        },
        "AdditionalProperties": {}
      }
    },
    {
      "capturedAt": "2026-06-17T23:15:06.0000000Z",
      "source": "ingest",
      "message": {
        "ActionRequiredByDateTime": null,
        "Attachments": null,
        "AttachmentsArchive": null,
        "Body": {
          "Content": "<p>PowerPoint Agent helps you build polished presentations with strong storytelling and visual structure. It streamlines research, formatting, and layout so you can stay focused on your message. Use multi‑turn chat to refine content or open the deck in PowerPoint for full editing and collaboration. Ideal for executive presentations, strategic updates, and market overviews. Available to Microsoft 365 users with or without a Microsoft 365 Copilot license.</p>\n<p><b>GA date:</b> March CY2026</p>\n<p><b>Preview date:</b> November CY2025</p>",
          "ContentType": "html",
          "Markdown": "PowerPoint Agent helps you build polished presentations with strong storytelling and visual structure. It streamlines research, formatting, and layout so you can stay focused on your message. Use multi‑turn chat to refine content or open the deck in PowerPoint for full editing and collaboration. Ideal for executive presentations, strategic updates, and market overviews. Available to Microsoft 365 users with or without a Microsoft 365 Copilot license.\n\nGA date: March CY2026\n\nPreview date: November CY2025"
        },
        "Category": "roadmap",
        "Details": [
          {
            "Name": "RoadmapIds",
            "Value": "543421"
          },
          {
            "Name": "SourceId",
            "Value": "543421"
          },
          {
            "Name": "RoadmapLink",
            "Value": "https://www.microsoft.com/microsoft-365/roadmap?id=543421"
          },
          {
            "Name": "Summary",
            "Value": "PowerPoint Agent helps you build polished presentations with strong storytelling and visual structure. It streamlines research, formatting, and layout so you can stay focused on your message. Use multi‑turn chat to refine content or open the deck in PowerPoint for full editing and collaboration. Ideal for executive presentations, strategic updates, and market overviews. Available to Microsoft 365 users with or without a Microsoft 365 Copilot license."
          },
          {
            "Name": "Status",
            "Value": "Launched"
          },
          {
            "Name": "ReleasePhase",
            "Value": "General Availability, Preview"
          },
          {
            "Name": "CloudInstances",
            "Value": "Worldwide (Standard Multi-Tenant)"
          },
          {
            "Name": "Platforms",
            "Value": "Desktop, Mac, Web"
          }
        ],
        "EndDateTime": null,
        "HasAttachments": false,
        "Id": "RM543421",
        "IsMajorChange": false,
        "LastModifiedDateTime": "2026-06-17T23:15:06.0000000Z",
        "Services": [
          "PowerPoint",
          "Microsoft Copilot (Microsoft 365)"
        ],
        "Severity": "normal",
        "Source": "roadmap",
        "StartDateTime": "2025-12-19T23:00:49.0000000Z",
        "Tags": [
          "Launched",
          "General Availability",
          "Preview",
          "Worldwide (Standard Multi-Tenant)"
        ],
        "Title": "Microsoft Copilot (Microsoft 365): PowerPoint Agent",
        "ViewPoint": {
          "IsArchived": null,
          "IsFavorited": null,
          "IsRead": null
        },
        "AdditionalProperties": {}
      }
    }
  ]
}