{
  "id": "RM559611",
  "versions": [
    {
      "capturedAt": "2026-04-03T22:15:57.0000000Z",
      "source": "git",
      "sha": "bc5eb4243809619b52baa0c9c57e4ec6dc6fcded",
      "message": {
        "ActionRequiredByDateTime": null,
        "Attachments": null,
        "AttachmentsArchive": null,
        "Body": {
          "Content": "<p>Presenters can now share a single application window and enable participants to annotate directly on top of that content, without exposing their entire desktop. This means cleaner presentations, protected privacy, and more engaging discussions across training sessions, workshops, and client meetings.</p>\n<p><b>GA date:</b> May CY2026</p>",
          "ContentType": "html",
          "Markdown": "Presenters can now share a single application window and enable participants to annotate directly on top of that content, without exposing their entire desktop. This means cleaner presentations, protected privacy, and more engaging discussions across training sessions, workshops, and client meetings.\n\nGA date: May CY2026"
        },
        "Category": "roadmap",
        "Details": [
          {
            "Name": "RoadmapIds",
            "Value": "559611"
          },
          {
            "Name": "SourceId",
            "Value": "559611"
          },
          {
            "Name": "RoadmapLink",
            "Value": "https://www.microsoft.com/microsoft-365/roadmap?id=559611"
          },
          {
            "Name": "Summary",
            "Value": "Presenters can now share a single application window and enable participants to annotate directly on top of that content, without exposing their entire desktop. This means cleaner presentations, protected privacy, and more engaging discussions across training sessions, workshops, and client meetings."
          },
          {
            "Name": "Status",
            "Value": "In development"
          },
          {
            "Name": "ReleasePhase",
            "Value": "General Availability, Targeted Release"
          },
          {
            "Name": "CloudInstances",
            "Value": "Worldwide (Standard Multi-Tenant)"
          },
          {
            "Name": "Platforms",
            "Value": "Mac"
          }
        ],
        "EndDateTime": null,
        "HasAttachments": false,
        "Id": "RM559611",
        "IsMajorChange": false,
        "LastModifiedDateTime": "2026-04-03T22:15:57.0000000Z",
        "Services": [
          "Microsoft Teams"
        ],
        "Severity": "normal",
        "Source": "roadmap",
        "StartDateTime": "2026-04-02T23:15:15.0000000Z",
        "Tags": [
          "In development",
          "General Availability",
          "Targeted Release",
          "Worldwide (Standard Multi-Tenant)"
        ],
        "Title": "Microsoft Teams: Annotations on Teams Single Window Sharing on macOS",
        "ViewPoint": {
          "IsArchived": null,
          "IsFavorited": null,
          "IsRead": null
        },
        "AdditionalProperties": {}
      }
    },
    {
      "capturedAt": "2026-05-01T21:45:13.0000000Z",
      "source": "git",
      "sha": "6b698ceb2ab33fea0b8ecfc35a0df611fe1f91b8",
      "message": {
        "ActionRequiredByDateTime": null,
        "Attachments": null,
        "AttachmentsArchive": null,
        "Body": {
          "Content": "<p>Presenters can now share a single application window and enable participants to annotate directly on top of that content, without exposing their entire desktop. This means cleaner presentations, protected privacy, and more engaging discussions across training sessions, workshops, and client meetings.</p>\n<p><b>GA date:</b> May CY2026</p>",
          "ContentType": "html",
          "Markdown": "Presenters can now share a single application window and enable participants to annotate directly on top of that content, without exposing their entire desktop. This means cleaner presentations, protected privacy, and more engaging discussions across training sessions, workshops, and client meetings.\n\nGA date: May CY2026"
        },
        "Category": "roadmap",
        "Details": [
          {
            "Name": "RoadmapIds",
            "Value": "559611"
          },
          {
            "Name": "SourceId",
            "Value": "559611"
          },
          {
            "Name": "RoadmapLink",
            "Value": "https://www.microsoft.com/microsoft-365/roadmap?id=559611"
          },
          {
            "Name": "Summary",
            "Value": "Presenters can now share a single application window and enable participants to annotate directly on top of that content, without exposing their entire desktop. This means cleaner presentations, protected privacy, and more engaging discussions across training sessions, workshops, and client meetings."
          },
          {
            "Name": "Status",
            "Value": "Rolling out"
          },
          {
            "Name": "ReleasePhase",
            "Value": "General Availability, Targeted Release"
          },
          {
            "Name": "CloudInstances",
            "Value": "Worldwide (Standard Multi-Tenant)"
          },
          {
            "Name": "Platforms",
            "Value": "Mac"
          }
        ],
        "EndDateTime": null,
        "HasAttachments": false,
        "Id": "RM559611",
        "IsMajorChange": false,
        "LastModifiedDateTime": "2026-05-01T21:45:13.0000000Z",
        "Services": [
          "Microsoft Teams"
        ],
        "Severity": "normal",
        "Source": "roadmap",
        "StartDateTime": "2026-04-02T23:15:15.0000000Z",
        "Tags": [
          "Rolling out",
          "General Availability",
          "Targeted Release",
          "Worldwide (Standard Multi-Tenant)"
        ],
        "Title": "Microsoft Teams: Annotations on Teams Single Window Sharing on macOS",
        "ViewPoint": {
          "IsArchived": null,
          "IsFavorited": null,
          "IsRead": null
        },
        "AdditionalProperties": {}
      }
    }
  ]
}