{
  "id": "RM562051",
  "versions": [
    {
      "capturedAt": "2026-05-12T23:00:33.0000000Z",
      "source": "ingest",
      "message": {
        "ActionRequiredByDateTime": null,
        "Attachments": null,
        "AttachmentsArchive": null,
        "Body": {
          "Content": "<p>When DLP rules detect policy violations in Exchange Online, they generate audit records that administrators rely on for compliance monitoring, incident investigation, and policy tuning. Previously, these records only showed Sensitive Information Type matches. This feature aims to extend that to sender domain, subject keywords, attachment type, or recipient information. Now they will be visible in alerts and Activity Explorer providing data enrichment to the administrators.</p>\n<p><b>GA date:</b> June CY2026</p>\n<p><b>Preview date:</b> May CY2026</p>",
          "ContentType": "html",
          "Markdown": "When DLP rules detect policy violations in Exchange Online, they generate audit records that administrators rely on for compliance monitoring, incident investigation, and policy tuning. Previously, these records only showed Sensitive Information Type matches. This feature aims to extend that to sender domain, subject keywords, attachment type, or recipient information. Now they will be visible in alerts and Activity Explorer providing data enrichment to the administrators.\n\nGA date: June CY2026\n\nPreview date: May CY2026"
        },
        "Category": "roadmap",
        "Details": [
          {
            "Name": "RoadmapIds",
            "Value": "562051"
          },
          {
            "Name": "SourceId",
            "Value": "562051"
          },
          {
            "Name": "RoadmapLink",
            "Value": "https://www.microsoft.com/microsoft-365/roadmap?id=562051"
          },
          {
            "Name": "Summary",
            "Value": "When DLP rules detect policy violations in Exchange Online, they generate audit records that administrators rely on for compliance monitoring, incident investigation, and policy tuning. Previously, these records only showed Sensitive Information Type matches. This feature aims to extend that to sender domain, subject keywords, attachment type, or recipient information. Now they will be visible in alerts and Activity Explorer providing data enrichment to the administrators."
          },
          {
            "Name": "Status",
            "Value": "In development"
          },
          {
            "Name": "ReleasePhase",
            "Value": "General Availability, Preview"
          },
          {
            "Name": "CloudInstances",
            "Value": "Worldwide (Standard Multi-Tenant)"
          },
          {
            "Name": "Platforms",
            "Value": "Web"
          }
        ],
        "EndDateTime": null,
        "HasAttachments": false,
        "Id": "RM562051",
        "IsMajorChange": false,
        "LastModifiedDateTime": "2026-05-12T23:00:33.0000000Z",
        "Services": [
          "Microsoft Purview"
        ],
        "Severity": "normal",
        "Source": "roadmap",
        "StartDateTime": "2026-05-12T23:00:33.0000000Z",
        "Tags": [
          "In development",
          "General Availability",
          "Preview",
          "Worldwide (Standard Multi-Tenant)"
        ],
        "Title": "Microsoft Purview: Data Loss Prevention - Enriched Audit Data for Matched Rules",
        "ViewPoint": {
          "IsArchived": null,
          "IsFavorited": null,
          "IsRead": null
        },
        "AdditionalProperties": {}
      }
    }
  ]
}