{
  "id": "RM565218",
  "versions": [
    {
      "capturedAt": "2026-06-09T20:46:16.0000000Z",
      "source": "ingest",
      "message": {
        "ActionRequiredByDateTime": null,
        "Attachments": null,
        "AttachmentsArchive": null,
        "Body": {
          "Content": "<p>We’re excited to announce that the Queues app is now available in the GCC High cloud. This Teams-native app helps organizations manage customer engagements more efficiently by bringing advanced call queue and auto attendant capabilities directly into Teams. Queues app is a Teams Premium feature. For more information about Queues app, including licensing information, please see Manage Queues app for Microsoft Teams in your organization.</p>\n<p><b>GA date:</b> July CY2026</p>",
          "ContentType": "html",
          "Markdown": "We’re excited to announce that the Queues app is now available in the GCC High cloud. This Teams-native app helps organizations manage customer engagements more efficiently by bringing advanced call queue and auto attendant capabilities directly into Teams. Queues app is a Teams Premium feature. For more information about Queues app, including licensing information, please see Manage Queues app for Microsoft Teams in your organization.\n\nGA date: July CY2026"
        },
        "Category": "roadmap",
        "Details": [
          {
            "Name": "RoadmapIds",
            "Value": "565218"
          },
          {
            "Name": "SourceId",
            "Value": "565218"
          },
          {
            "Name": "RoadmapLink",
            "Value": "https://www.microsoft.com/microsoft-365/roadmap?id=565218"
          },
          {
            "Name": "Summary",
            "Value": "We’re excited to announce that the Queues app is now available in the GCC High cloud. This Teams-native app helps organizations manage customer engagements more efficiently by bringing advanced call queue and auto attendant capabilities directly into Teams. Queues app is a Teams Premium feature. For more information about Queues app, including licensing information, please see Manage Queues app for Microsoft Teams in your organization."
          },
          {
            "Name": "Status",
            "Value": "In development"
          },
          {
            "Name": "ReleasePhase",
            "Value": "General Availability"
          },
          {
            "Name": "CloudInstances",
            "Value": "GCC High, Worldwide (Standard Multi-Tenant)"
          },
          {
            "Name": "Platforms",
            "Value": "Desktop, Mac"
          }
        ],
        "EndDateTime": null,
        "HasAttachments": false,
        "Id": "RM565218",
        "IsMajorChange": false,
        "LastModifiedDateTime": "2026-06-09T20:46:16.0000000Z",
        "Services": [
          "Microsoft Teams"
        ],
        "Severity": "normal",
        "Source": "roadmap",
        "StartDateTime": "2026-06-09T20:46:16.0000000Z",
        "Tags": [
          "In development",
          "General Availability",
          "Worldwide (Standard Multi-Tenant)",
          "GCC High"
        ],
        "Title": "Microsoft Teams: Queues app for Microsoft Teams in GCC High",
        "ViewPoint": {
          "IsArchived": null,
          "IsFavorited": null,
          "IsRead": null
        },
        "AdditionalProperties": {}
      }
    },
    {
      "capturedAt": "2026-06-10T23:00:02.0000000Z",
      "source": "ingest",
      "message": {
        "ActionRequiredByDateTime": null,
        "Attachments": null,
        "AttachmentsArchive": null,
        "Body": {
          "Content": "<p>We’re excited to announce that the Queues app is now available in the GCC High cloud. This Teams-native app helps organizations manage customer engagements more efficiently by bringing advanced call queue and auto attendant capabilities directly into Teams. Queues app is a Teams Premium feature. For more information about Queues app, including licensing information, please see Manage Queues app for Microsoft Teams in your organization.</p>\n<p><b>GA date:</b> July CY2026</p>",
          "ContentType": "html",
          "Markdown": "We’re excited to announce that the Queues app is now available in the GCC High cloud. This Teams-native app helps organizations manage customer engagements more efficiently by bringing advanced call queue and auto attendant capabilities directly into Teams. Queues app is a Teams Premium feature. For more information about Queues app, including licensing information, please see Manage Queues app for Microsoft Teams in your organization.\n\nGA date: July CY2026"
        },
        "Category": "roadmap",
        "Details": [
          {
            "Name": "RoadmapIds",
            "Value": "565218"
          },
          {
            "Name": "SourceId",
            "Value": "565218"
          },
          {
            "Name": "RoadmapLink",
            "Value": "https://www.microsoft.com/microsoft-365/roadmap?id=565218"
          },
          {
            "Name": "Summary",
            "Value": "We’re excited to announce that the Queues app is now available in the GCC High cloud. This Teams-native app helps organizations manage customer engagements more efficiently by bringing advanced call queue and auto attendant capabilities directly into Teams. Queues app is a Teams Premium feature. For more information about Queues app, including licensing information, please see Manage Queues app for Microsoft Teams in your organization."
          },
          {
            "Name": "Status",
            "Value": "In development"
          },
          {
            "Name": "ReleasePhase",
            "Value": "General Availability"
          },
          {
            "Name": "CloudInstances",
            "Value": "GCC High"
          },
          {
            "Name": "Platforms",
            "Value": "Desktop, Mac"
          }
        ],
        "EndDateTime": null,
        "HasAttachments": false,
        "Id": "RM565218",
        "IsMajorChange": false,
        "LastModifiedDateTime": "2026-06-10T23:00:02.0000000Z",
        "Services": [
          "Microsoft Teams"
        ],
        "Severity": "normal",
        "Source": "roadmap",
        "StartDateTime": "2026-06-09T20:46:16.0000000Z",
        "Tags": [
          "In development",
          "General Availability",
          "GCC High"
        ],
        "Title": "Microsoft Teams: Queues app for Microsoft Teams in GCC High",
        "ViewPoint": {
          "IsArchived": null,
          "IsFavorited": null,
          "IsRead": null
        },
        "AdditionalProperties": {}
      }
    },
    {
      "capturedAt": "2026-06-16T23:00:10.0000000Z",
      "source": "ingest",
      "message": {
        "ActionRequiredByDateTime": null,
        "Attachments": null,
        "AttachmentsArchive": null,
        "Body": {
          "Content": "<p>We’re excited to announce that the Queues app is now available in the GCC High and DoD clouds. This Teams-native app helps organizations manage customer engagements more efficiently by bringing advanced call queue and auto attendant capabilities directly into Teams. Queues app is a Teams Premium feature. For more information about Queues app, including licensing information, please see Manage Queues app for Microsoft Teams in your organization.</p>\n<p><b>GA date:</b> July CY2026</p>",
          "ContentType": "html",
          "Markdown": "We’re excited to announce that the Queues app is now available in the GCC High and DoD clouds. This Teams-native app helps organizations manage customer engagements more efficiently by bringing advanced call queue and auto attendant capabilities directly into Teams. Queues app is a Teams Premium feature. For more information about Queues app, including licensing information, please see Manage Queues app for Microsoft Teams in your organization.\n\nGA date: July CY2026"
        },
        "Category": "roadmap",
        "Details": [
          {
            "Name": "RoadmapIds",
            "Value": "565218"
          },
          {
            "Name": "SourceId",
            "Value": "565218"
          },
          {
            "Name": "RoadmapLink",
            "Value": "https://www.microsoft.com/microsoft-365/roadmap?id=565218"
          },
          {
            "Name": "Summary",
            "Value": "We’re excited to announce that the Queues app is now available in the GCC High and DoD clouds. This Teams-native app helps organizations manage customer engagements more efficiently by bringing advanced call queue and auto attendant capabilities directly into Teams. Queues app is a Teams Premium feature. For more information about Queues app, including licensing information, please see Manage Queues app for Microsoft Teams in your organization."
          },
          {
            "Name": "Status",
            "Value": "In development"
          },
          {
            "Name": "ReleasePhase",
            "Value": "General Availability"
          },
          {
            "Name": "CloudInstances",
            "Value": "DoD, GCC High"
          },
          {
            "Name": "Platforms",
            "Value": "Desktop, Mac"
          }
        ],
        "EndDateTime": null,
        "HasAttachments": false,
        "Id": "RM565218",
        "IsMajorChange": false,
        "LastModifiedDateTime": "2026-06-16T23:00:10.0000000Z",
        "Services": [
          "Microsoft Teams"
        ],
        "Severity": "normal",
        "Source": "roadmap",
        "StartDateTime": "2026-06-09T20:46:16.0000000Z",
        "Tags": [
          "In development",
          "General Availability",
          "GCC High",
          "DoD"
        ],
        "Title": "Microsoft Teams: Queues app for Microsoft Teams in GCC High and DoD",
        "ViewPoint": {
          "IsArchived": null,
          "IsFavorited": null,
          "IsRead": null
        },
        "AdditionalProperties": {}
      }
    }
  ]
}