{
  "id": "RM560708",
  "versions": [
    {
      "capturedAt": "2026-04-21T23:00:01.0000000Z",
      "source": "git",
      "sha": "bc5eb4243809619b52baa0c9c57e4ec6dc6fcded",
      "message": {
        "ActionRequiredByDateTime": null,
        "Attachments": null,
        "AttachmentsArchive": null,
        "Body": {
          "Content": "<p>AI-powered intent for classifiers: Microsoft Purview Information Protection will generate a human-readable semantic intent for custom Sensitive Information Types (SITs), helping customers better understand what their classifiers detect and refine them for higher accuracy and fewer false positives.</p>\n<p><b>GA date:</b> June CY2026</p>\n<p><b>Preview date:</b> May CY2026</p>",
          "ContentType": "html",
          "Markdown": "AI-powered intent for classifiers: Microsoft Purview Information Protection will generate a human-readable semantic intent for custom Sensitive Information Types (SITs), helping customers better understand what their classifiers detect and refine them for higher accuracy and fewer false positives.\n\nGA date: June CY2026\n\nPreview date: May CY2026"
        },
        "Category": "roadmap",
        "Details": [
          {
            "Name": "RoadmapIds",
            "Value": "560708"
          },
          {
            "Name": "SourceId",
            "Value": "560708"
          },
          {
            "Name": "RoadmapLink",
            "Value": "https://www.microsoft.com/microsoft-365/roadmap?id=560708"
          },
          {
            "Name": "Summary",
            "Value": "AI-powered intent for classifiers: Microsoft Purview Information Protection will generate a human-readable semantic intent for custom Sensitive Information Types (SITs), helping customers better understand what their classifiers detect and refine them for higher accuracy and fewer false positives."
          },
          {
            "Name": "Status",
            "Value": "In development"
          },
          {
            "Name": "ReleasePhase",
            "Value": "General Availability, Preview"
          },
          {
            "Name": "CloudInstances",
            "Value": "Worldwide (Standard Multi-Tenant)"
          },
          {
            "Name": "Platforms",
            "Value": "Web"
          }
        ],
        "EndDateTime": null,
        "HasAttachments": false,
        "Id": "RM560708",
        "IsMajorChange": false,
        "LastModifiedDateTime": "2026-04-21T23:00:01.0000000Z",
        "Services": [
          "Microsoft Purview"
        ],
        "Severity": "normal",
        "Source": "roadmap",
        "StartDateTime": "2026-04-21T23:00:01.0000000Z",
        "Tags": [
          "In development",
          "General Availability",
          "Preview",
          "Worldwide (Standard Multi-Tenant)"
        ],
        "Title": "Microsoft Purview: Information Protection – AI-powered intent for classifiers",
        "ViewPoint": {
          "IsArchived": null,
          "IsFavorited": null,
          "IsRead": null
        },
        "AdditionalProperties": {}
      }
    },
    {
      "capturedAt": "2026-06-30T22:57:58.0000000Z",
      "source": "ingest",
      "message": {
        "ActionRequiredByDateTime": null,
        "Attachments": null,
        "AttachmentsArchive": null,
        "Body": {
          "Content": "<p>AI-powered intent for classifiers: Microsoft Purview Information Protection will generate a human-readable semantic intent for custom Sensitive Information Types (SITs), helping customers better understand what their classifiers detect and refine them for higher accuracy and fewer false positives.</p>\n<p><b>GA date:</b> September CY2026</p>\n<p><b>Preview date:</b> August CY2026</p>",
          "ContentType": "html",
          "Markdown": "AI-powered intent for classifiers: Microsoft Purview Information Protection will generate a human-readable semantic intent for custom Sensitive Information Types (SITs), helping customers better understand what their classifiers detect and refine them for higher accuracy and fewer false positives.\n\nGA date: September CY2026\n\nPreview date: August CY2026"
        },
        "Category": "roadmap",
        "Details": [
          {
            "Name": "RoadmapIds",
            "Value": "560708"
          },
          {
            "Name": "SourceId",
            "Value": "560708"
          },
          {
            "Name": "RoadmapLink",
            "Value": "https://www.microsoft.com/microsoft-365/roadmap?id=560708"
          },
          {
            "Name": "Summary",
            "Value": "AI-powered intent for classifiers: Microsoft Purview Information Protection will generate a human-readable semantic intent for custom Sensitive Information Types (SITs), helping customers better understand what their classifiers detect and refine them for higher accuracy and fewer false positives."
          },
          {
            "Name": "Status",
            "Value": "In development"
          },
          {
            "Name": "ReleasePhase",
            "Value": "General Availability, Preview"
          },
          {
            "Name": "CloudInstances",
            "Value": "Worldwide (Standard Multi-Tenant)"
          },
          {
            "Name": "Platforms",
            "Value": "Web"
          }
        ],
        "EndDateTime": null,
        "HasAttachments": false,
        "Id": "RM560708",
        "IsMajorChange": false,
        "LastModifiedDateTime": "2026-06-30T22:57:58.0000000Z",
        "Services": [
          "Microsoft Purview"
        ],
        "Severity": "normal",
        "Source": "roadmap",
        "StartDateTime": "2026-04-21T23:00:01.0000000Z",
        "Tags": [
          "In development",
          "General Availability",
          "Preview",
          "Worldwide (Standard Multi-Tenant)"
        ],
        "Title": "Microsoft Purview: Information Protection – AI-powered intent for classifiers",
        "ViewPoint": {
          "IsArchived": null,
          "IsFavorited": null,
          "IsRead": null
        },
        "AdditionalProperties": {}
      }
    }
  ]
}