{
  "ActionRequiredByDateTime": null,
  "Attachments": null,
  "AttachmentsArchive": null,
  "Body": {
    "Content": "<p>Coming soon: Users can create images using natural language to visualize concepts and ideas in the flow of work in iOS/Android mobile apps for Microsoft 365 Copilot, Microsoft Teams, and Microsoft Outlook.</p><p>\n</p><p>A Microsoft 365 Copilot license or a Microsoft 365 license is required to use this feature.</p><p><b>When this will happen:</b>\n</p><p>General Availability (Worldwide): We will begin rolling out on mid-April 2025 and expect to complete by late April 2025.\n</p><p><b>How this will affect your organization:</b>\n</p><p>This new feature will be available by default.</p><p>\n</p><p>In the <i>Chat </i>tab of the Microsoft 365 Copilot mobile app, users can enter natural language to ask Copilot to generate an image:\n</p><p><img src=\"https://cxcs.microsoft.net/file/ccp/en-us/675e89b4-adb2-464c-b2b4-029f2d5aedce\" style=\"width: 400px;\" alt=\"user controls\">\n</p><p><b>What you need to do to prepare:</b>\n</p><p>This rollout will happen automatically with no admin action required. You may want to notify your users about this change and update any relevant documentation as appropriate.</p>",
    "ContentType": "html"
  },
  "Category": "stayInformed",
  "Details": [],
  "EndDateTime": "2025-07-25T07:00:00Z",
  "HasAttachments": false,
  "Id": "MC1052161",
  "IsMajorChange": false,
  "LastModifiedDateTime": "2025-04-10T01:44:20.807Z",
  "Services": [
    "Microsoft 365 suite"
  ],
  "Severity": "normal",
  "StartDateTime": "2025-04-10T01:43:58Z",
  "Tags": [
    "New feature",
    "User impact"
  ],
  "Title": "Microsoft 365 Copilot mobile apps: Generate images",
  "ViewPoint": {
    "IsArchived": null,
    "IsFavorited": null,
    "IsRead": null
  },
  "AdditionalProperties": {}
}
