{
  "ActionRequiredByDateTime": null,
  "Attachments": null,
  "AttachmentsArchive": null,
  "Body": {
    "Content": "We are announcing the create and edit expressions with Copilot feature for Power Automate. With this feature, makers can create, edit, and fix their Power Automate expressions by invoking Copilot. This feature will reach general availability on September 15, 2024.<br><br><b>How does this affect me?</b><br>Makers can create complex expressions or edit their existing expressions simply by submitting natural language prompts to Copilot in Power Automate.<br><br><b>What do I need to do to prepare?</b><br>This message is for awareness and no action is required.<br><br>For more information on this feature, please visit <a href=\"https://aka.ms/ADO7963\" target=\"_blank\">Create and edit expressions with Copilot</a>.",
    "ContentType": "html"
  },
  "Category": "stayInformed",
  "Details": [],
  "EndDateTime": "2024-09-08T14:22:56Z",
  "HasAttachments": false,
  "Id": "MC855250",
  "IsMajorChange": false,
  "LastModifiedDateTime": "2024-08-08T14:23:27.01Z",
  "Services": [
    "Microsoft Power Automate"
  ],
  "Severity": "normal",
  "StartDateTime": "2024-08-08T14:22:56Z",
  "Tags": [
    "New feature"
  ],
  "Title": "Power Automate – Create and edit expressions with Copilot announcement",
  "ViewPoint": {
    "IsArchived": null,
    "IsFavorited": null,
    "IsRead": null
  },
  "AdditionalProperties": {}
}
