{
  "ActionRequiredByDateTime": null,
  "Attachments": null,
  "AttachmentsArchive": null,
  "Body": {
    "Content": "<p>Users are now able hide their favorites section in Microsoft Outlook, which provides more space in the folder pane.</p>\n<p>This message is associated with Microsoft 365 Roadmap ID <a href=\"https://www.microsoft.com/microsoft-365/roadmap?filters=&amp;searchterms=167071\" target=\"_blank\">167071</a></p>\n<p>[When this will happen:]</p>\n\n<p>Standard Release: Rollout started late October 2023 and is expected to complete by late February 2024.</p><p>GCC, GCCHigh, and DoD Release: Rollout will start late February 2024 and is expected to complete early March 2024.</p>\n\n<p>[How this will affect your organization:]</p>\n\n<p>Users now have the flexibility to configure the visibility of the favorites section in the folder pane. To adjust these settings:</p><ul><li>Navigate to the 'View' tab &gt; 'Layout' &gt; 'Folder Pane' &gt; 'Favorites.' Here, you can choose to 'Show' or 'Hide' your favorites.</li><li>Alternatively, right-click on the favorites section and select 'Hide favorites' to conceal the entire section.</li><li>If you add a Folder, Category, or Person to your favorites, the favorites section will automatically reappear.</li></ul><p>[What you need to do to prepare:]</p><p>There is no action needed to prepare for this change. You may want to notify your users about this change and update any relevant documentation as appropriate.</p>",
    "ContentType": "html"
  },
  "Category": "stayInformed",
  "Details": [
    {
      "Name": "RoadmapIds",
      "Value": "167071"
    },
    {
      "Name": "Platforms",
      "Value": "Web"
    },
    {
      "Name": "BlogLink",
      "Value": "https://support.microsoft.com/office/use-favorites-in-outlook-8913f2d0-b167-48cc-8983-86fa9b0d945f"
    },
    {
      "Name": "HelpLink",
      "Value": "https://support.microsoft.com/office/use-favorites-in-outlook-8913f2d0-b167-48cc-8983-86fa9b0d945f"
    }
  ],
  "EndDateTime": "2024-04-08T07:00:00Z",
  "HasAttachments": false,
  "Id": "MC709262",
  "IsMajorChange": false,
  "LastModifiedDateTime": "2024-01-23T00:38:27.293Z",
  "Services": [
    "Microsoft 365 for the web",
    "Microsoft 365 apps"
  ],
  "Severity": "normal",
  "StartDateTime": "2024-01-23T00:37:57Z",
  "Tags": [
    "New feature",
    "User impact"
  ],
  "Title": "Microsoft Outlook: Hide favorites in the New Outlook for Windows and web",
  "ViewPoint": {
    "IsArchived": null,
    "IsFavorited": null,
    "IsRead": null
  },
  "AdditionalProperties": {}
}
